

[
  
  { "title": "Bash: Προσθέτοντας tab συμπλήρωση στα script",
    "description": "Ένα βοήθημα σχετικά με το πως μπορείτε να προσθέσετε tab συμπλήρωση στα script σας σε περιβάλλον Bash",
    "date": "Nov 13, 2019 - 10:30",
    "categories": "programming",
    "tags": ["bash","linux","programmable-completion","opensource","tutorial","how-to","featured","δημοφιλή","γραμμή εντολών","ανοιχτό λογισμικό","βοήθημα"],
    "url": "https://iridakos.com/el/programming/2019/11/13/bash-programmable-completion-tutorial"},
  
  { "title": "Γράφοντας καλύτερα email",
    "description": "Συμβουλές για την σύνταξη αποτελεσματικών email αποφεύγοντας παρανοήσεις, με παραδείγματα από τον κόσμο της πληροφορικής.",
    "date": "Nov 11, 2019 - 23:10",
    "categories": "programming",
    "tags": ["email","επικοινωνία","παραγωγικότητα","how-to","featured","δημοφιλή"],
    "url": "https://iridakos.com/el/programming/2019/11/11/composing-better-emails"},
  
  { "title": "Αποδιπλοποίηση των γραμμών ενός αρχείου διατηρώντας τη σειρά τους",
    "description": "Πως να αφαιρέσετε τις διπλές γραμμές ενός αρχείο σε Linux χωρίς να αλλάξει η σειρά τους - επεξήγηση awk one-liner κώδικα.",
    "date": "Nov 11, 2019 - 23:05",
    "categories": "programming",
    "tags": ["linux","bash","scripts","file","awk","how-to","featured","δημοφιλή"],
    "url": "https://iridakos.com/el/programming/2019/11/11/remove-duplicate-lines-preserving-order-linux"},
  
  { "title": "Καναπές",
    "description": "&lt;p&gt;12 χρόνια μαζί.&lt;/p&gt;",
    "date": "Nov 9, 2019 - 23:30",
    "categories": "cats",
    "tags": ["photo","cat","irida","hanging-out"],
    "url": "https://iridakos.com/el/cats/2019/11/09/hug-the-cat"},
  
  { "title": "Two step authentication",
    "description": "&lt;p&gt;Υπάρχουν δύο γατοκρέβατα, τόσες καρέκλες και καναπές.&lt;/p&gt;",
    "date": "Nov 9, 2019 - 23:20",
    "categories": "cats",
    "tags": ["photo","cat","cats","two step authentication","humor","ubuntu"],
    "url": "https://iridakos.com/el/cats/2019/11/09/two-step-authentication"},
  
  { "title": "Ζωγραφίζοντας βουνά με τον Μπομπ Ρος",
    "description": "Ζωγραφίζοντας ένα τοπίο με βουνά ακολουθώντας το επεισόδιο 10 από τη σεζόν 13 της εκπομπής &#39;Η χαρά της ζωγραφικής&#39; του Μπομπ Ρος.",
    "date": "Oct 14, 2019 - 17:00",
    "categories": "painting",
    "tags": ["painting","ζωγραφική","Bob Ross","Μπομπ Ρος","mountains","βουνά"],
    "url": "https://iridakos.com/el/painting/2019/10/14/mountains"},
  
  { "title": "Ζωγραφίζοντας λιβάδια με τον Μπομπ Ρος",
    "description": "Ζωγραφίζοντας ένα λιβάδι ακολουθώντας το επεισόδιο 13 από τη σεζόν 5 της εκπομπής &#39;Η χαρά της ζωγραφικής&#39; του Μπομπ Ρος.",
    "date": "Oct 11, 2019 - 10:00",
    "categories": "painting",
    "tags": ["painting","ζωγραφική","Bob Ross","Μπομπ Ρος","meadow","λιβάδι"],
    "url": "https://iridakos.com/el/painting/2019/10/11/meadow"},
  
  { "title": "Ζωγραφίζοντας τη γάτα μου",
    "description": "Η προσπάθεια μου να ζωγραφίσω τη γάτα μου που δε μοιάζει καθόλου με το αποτέλεσμα.",
    "date": "Oct 7, 2019 - 10:00",
    "categories": "",
    "tags": ["ζωγραφική","painting","cats","γάτες","τέχνη","πικάτσο"],
    "url": "https://iridakos.com/el/painting/2019/10/07/drawing-my-cat"},
  
  { "title": "Παρασκευή",
    "description": "",
    "date": "Oct 1, 2019 - 00:01",
    "categories": "",
    "tags": ["friday","Παρασκευή"],
    "url": "https://iridakos.com/el/cats/2019/10/01/another-friday"},
  
  { "title": "Pair programming",
    "description": "",
    "date": "Oct 1, 2019 - 00:01",
    "categories": "",
    "tags": ["pair programming"],
    "url": "https://iridakos.com/el/cats/2019/10/01/pair-programming"},
  
  { "title": "Δευτέρα. Πάλι.",
    "description": "",
    "date": "Oct 1, 2019 - 00:01",
    "categories": "",
    "tags": ["monday","Δευτέρα","monday motivation"],
    "url": "https://iridakos.com/el/cats/2019/10/01/monday-again"},
  
  { "title": "Ηλεκτρική σκούπα",
    "description": "",
    "date": "Oct 1, 2019 - 00:01",
    "categories": "",
    "tags": [],
    "url": "https://iridakos.com/el/cats/2019/10/01/vacuum-cleaner"},
  
  { "title": "I'll be back",
    "description": "",
    "date": "Oct 1, 2019 - 00:01",
    "categories": "",
    "tags": [],
    "url": "https://iridakos.com/el/cats/2019/10/01/terminator"},
  
  { "title": "Δευτέρα",
    "description": "",
    "date": "Oct 1, 2019 - 00:01",
    "categories": "",
    "tags": ["monday","Δευτέρα","monday motivation"],
    "url": "https://iridakos.com/el/cats/2019/10/01/monday"},
  
  { "title": "Καληνύχτα",
    "description": "",
    "date": "Oct 1, 2019 - 00:01",
    "categories": "",
    "tags": [],
    "url": "https://iridakos.com/el/cats/2019/10/01/goot-night"},
  
  { "title": "Catwin Charles",
    "description": "",
    "date": "Oct 1, 2019 - 00:01",
    "categories": "",
    "tags": [],
    "url": "https://iridakos.com/el/cats/2019/10/01/catologist"},
  
  { "title": "Μπου",
    "description": "",
    "date": "Oct 1, 2019 - 00:01",
    "categories": "",
    "tags": [],
    "url": "https://iridakos.com/el/cats/2019/10/01/boo"},
  
  { "title": "Γατηγήτρια",
    "description": "",
    "date": "Oct 1, 2019 - 00:01",
    "categories": "",
    "tags": [],
    "url": "https://iridakos.com/el/cats/2019/10/01/i-know-stuff"},
  
  { "title": "I don't like reggae - I love it",
    "description": "",
    "date": "Oct 1, 2019 - 00:01",
    "categories": "",
    "tags": [],
    "url": "https://iridakos.com/el/cats/2019/10/01/code-review-mode"},
  
  { "title": "Ξαναφορτώνοντας τη σελίδα μετά από copy/paste CSS από stackoverflow",
    "description": "",
    "date": "Oct 1, 2019 - 00:01",
    "categories": "",
    "tags": [],
    "url": "https://iridakos.com/el/cats/2019/10/01/css-stackoveflow"},
  
  { "title": "Όταν στέλνουν κώδικα στο κλαδί σου",
    "description": "",
    "date": "Oct 1, 2019 - 00:01",
    "categories": "",
    "tags": [],
    "url": "https://iridakos.com/el/cats/2019/10/01/push-on-my-branch"},
  
  { "title": "Όταν βγαίνει pop up για Java update",
    "description": "",
    "date": "Oct 1, 2019 - 00:01",
    "categories": "",
    "tags": [],
    "url": "https://iridakos.com/el/cats/2019/10/01/java-update-popup"},
  
  { "title": "Κόλλα πέντε",
    "description": "",
    "date": "Oct 1, 2019 - 00:01",
    "categories": "",
    "tags": [],
    "url": "https://iridakos.com/el/cats/2019/10/01/friday-releases"},
  
  { "title": "Διαβάζοντας regular expressions",
    "description": "",
    "date": "Oct 1, 2019 - 00:01",
    "categories": "",
    "tags": [],
    "url": "https://iridakos.com/el/cats/2019/10/01/regex"},
  
  { "title": "Όταν πρέπει να υποστηρίξεις IE6",
    "description": "",
    "date": "Oct 1, 2019 - 00:01",
    "categories": "",
    "tags": [],
    "url": "https://iridakos.com/el/cats/2019/10/01/ie6"},
  
  { "title": "reCaptcha",
    "description": "",
    "date": "Oct 1, 2019 - 00:01",
    "categories": "",
    "tags": [],
    "url": "https://iridakos.com/el/cats/2019/10/01/recaptcha"},
  
  { "title": "Ruby",
    "description": "",
    "date": "Oct 1, 2019 - 00:01",
    "categories": "",
    "tags": [],
    "url": "https://iridakos.com/el/cats/2019/10/01/ruby-duck"},
  
  { "title": "GitHub issues",
    "description": "",
    "date": "Oct 1, 2019 - 00:01",
    "categories": "",
    "tags": [],
    "url": "https://iridakos.com/el/cats/2019/10/01/github-issue"},
  
  { "title": "RIP πουλόβερ",
    "description": "",
    "date": "Oct 1, 2019 - 00:01",
    "categories": "",
    "tags": [],
    "url": "https://iridakos.com/el/cats/2019/10/01/mutable-strings"},
  
  { "title": "Ψιτ",
    "description": "",
    "date": "Oct 1, 2019 - 00:01",
    "categories": "",
    "tags": [],
    "url": "https://iridakos.com/el/cats/2019/10/01/code-comments"},
  
  { "title": "Δουλεύοντας με αυτό στο πλάι",
    "description": "",
    "date": "Oct 1, 2019 - 00:01",
    "categories": "",
    "tags": [],
    "url": "https://iridakos.com/el/cats/2019/10/01/introducing-the-programming-cat"},
  
  { "title": "Cat HTTP status codes",
    "description": "My cats in http status codes.",
    "date": "Sep 26, 2016 - 21:00",
    "categories": "cats",
    "tags": ["cats","http","programming","humor","devhumor"],
    "url": "https://iridakos.com/el/cats/2016/09/26/cat-http-status-codes"}]
